osc_placement_tree/__init__.py
osc_placement_tree/dot.py
osc_placement_tree/graph.py
osc_placement_tree/html.py
osc_placement_tree/http.py
osc_placement_tree/plugin.py
osc_placement_tree/tree.py
osc_placement_tree/utils.py
osc_placement_tree/resources/__init__.py
osc_placement_tree/resources/provider_tree.py
osc_placement_tree/tests/__init__.py
osc_placement_tree/tests/base.py
osc_placement_tree/tests/uuids.py
osc_placement_tree/tests/functional/__init__.py
osc_placement_tree/tests/functional/base.py
osc_placement_tree/tests/functional/test_provider_tree.py
osc_placement_tree/tests/unit/__init__.py
osc_placement_tree/tests/unit/test_dot.py
osc_placement_tree/tests/unit/test_html.py
osc_placement_tree/tests/unit/test_provider_tree.py
osc_placement_tree/tests/unit/test_tree.py
osc_placement_tree-0.2.0.dist-info/DESCRIPTION.rst
osc_placement_tree-0.2.0.dist-info/METADATA
osc_placement_tree-0.2.0.dist-info/RECORD
osc_placement_tree-0.2.0.dist-info/WHEEL
osc_placement_tree-0.2.0.dist-info/entry_points.txt
osc_placement_tree-0.2.0.dist-info/metadata.json
osc_placement_tree-0.2.0.dist-info/pbr.json
osc_placement_tree-0.2.0.dist-info/top_level.txt
