Metadata-Version: 2.0
Name: osc-placement-tree
Version: 0.2.0
Summary: OpenStackClient plugin for advanced operations for the Placement service
Home-page: https://github.com/gibizer/osc-placement-tree
Author: Balazs Gibizer
Author-email: gibizer@gmail.com
License: UNKNOWN
Platform: UNKNOWN
Classifier: Environment :: OpenStack
Classifier: Intended Audience :: Information Technology
Classifier: Intended Audience :: System Administrators
Classifier: License :: OSI Approved :: Apache Software License
Classifier: Operating System :: POSIX :: Linux
Classifier: Programming Language :: Python
Classifier: Programming Language :: Python :: 2
Classifier: Programming Language :: Python :: 2.7
Classifier: Programming Language :: Python :: 3
Classifier: Programming Language :: Python :: 3.6
Requires-Dist: graphviz (>=0.8.4)
Requires-Dist: keystoneauth1 (>=3.3.0)
Requires-Dist: osc-lib (>=1.2.0)
Requires-Dist: pbr (>=2.0.0)
Requires-Dist: six (>=1.10.0)
